{"nodes": [{"id": "hooks_useapi_load", "label": "useApi load callback", "file_type": "code", "source_file": "client/src/hooks/useApi.js", "source_location": "L8", "source_url": null, "captured_at": null, "author": null, "contributor": null}], "edges": [{"source": "hooks_useapi_load", "target": "api_endpoints_dashboard", "relation": "calls", "confidence": "INFERRED", "confidence_score": 0.8, "source_file": "client/src/hooks/useApi.js", "source_location": "L12", "weight": 1.0}, {"source": "hooks_useapi_load", "target": "api_endpoints_experiences", "relation": "calls", "confidence": "INFERRED", "confidence_score": 0.8, "source_file": "client/src/hooks/useApi.js", "source_location": "L12", "weight": 1.0}, {"source": "hooks_useapi_load", "target": "api_endpoints_skills", "relation": "calls", "confidence": "INFERRED", "confidence_score": 0.8, "source_file": "client/src/hooks/useApi.js", "source_location": "L12", "weight": 1.0}, {"source": "hooks_useapi_load", "target": "api_endpoints_badges", "relation": "calls", "confidence": "INFERRED", "confidence_score": 0.8, "source_file": "client/src/hooks/useApi.js", "source_location": "L12", "weight": 1.0}, {"source": "hooks_useapi_useapi", "target": "hooks_useapi_load", "relation": "calls", "confidence": "EXTRACTED", "confidence_score": 1.0, "source_file": "client/src/hooks/useApi.js", "source_location": "L21", "weight": 1.0}], "hyperedges": [{"id": "useapi_data_fetching", "label": "useApi hook data fetching across pages", "nodes": ["hooks_useapi_useapi", "hooks_useapi_load", "pages_badges_badges", "pages_dashboard_dashboard", "pages_skills_skills", "pages_timeline_timeline"], "relation": "form", "confidence": "INFERRED", "confidence_score": 0.85, "source_file": "client/src/hooks/useApi.js"}]}